nn_wtf/__init__.py
nn_wtf/data_set_base.py
nn_wtf/data_sets.py
nn_wtf/images_labels_data_set.py
nn_wtf/input_data.py
nn_wtf/mnist_data_sets.py
nn_wtf/mnist_graph.py
nn_wtf/neural_network_graph.py
nn_wtf/neural_network_graph_base.py
nn_wtf/neural_network_graph_mixin.py
nn_wtf/predictor.py
nn_wtf/saver_mixin.py
nn_wtf/summary_writer_mixin.py
nn_wtf/trainer.py
nn_wtf/data/1_from_test_set.raw
nn_wtf/data/2_from_test_set.raw
nn_wtf/data/4_from_test_set.raw
nn_wtf/data/7_2.raw
nn_wtf/data/7_2_1.raw
nn_wtf/data/7_2_1_0.raw
nn_wtf/data/7_2_1_0_4.raw
nn_wtf/data/7_from_test_set.raw
nn_wtf/data/convert_numbers.sh
nn_wtf/data/extract_numbers_from_test_set.sh
nn_wtf/data/results.py
nn_wtf/tests/__init__.py
nn_wtf/tests/images_labels_data_set_test.py
nn_wtf/tests/input_data_test.py
nn_wtf/tests/neural_network_graph_test.py
nn_wtf/tests/neural_network_optimizer_test.py
nn_wtf/tests/predictor_test.py
nn_wtf/tests/run_tests.py
nn_wtf/tests/save_and_restore_test.py
nn_wtf/tests/trainer_test.py
nn_wtf/tests/util.py
nn_wtf-0.1.7.dist-info/DESCRIPTION.rst
nn_wtf-0.1.7.dist-info/METADATA
nn_wtf-0.1.7.dist-info/RECORD
nn_wtf-0.1.7.dist-info/WHEEL
nn_wtf-0.1.7.dist-info/metadata.json
nn_wtf-0.1.7.dist-info/top_level.txt
