Metadata-Version: 2.0
Name: nn-wtf
Version: 0.1.7
Summary: Neural Networks Wrapper for TensorFlow
Home-page: http://github.com/lene/nn-wtf
Author: Lene Preuss
Author-email: lene.preuss@gmail.com
License: Apache Software License V2
Keywords: machine learning neural networks tensorflow
Platform: UNKNOWN
Classifier: Development Status :: 2 - Pre-Alpha
Classifier: License :: OSI Approved :: Apache Software License
Classifier: Programming Language :: Python :: 3.4
Classifier: Topic :: Software Development :: Libraries :: Python Modules
Requires-Dist: numpy
Requires-Dist: tensorflow
